guipy/__init__.py
guipy/__version__.py
guipy/_globals.py
guipy/app/__init__.py
guipy/app/main_window.py
guipy/app/start.py
guipy/config/__init__.py
guipy/config/base.py
guipy/config/core.py
guipy/config/dialog.py
guipy/config/general.py
guipy/config/manager.py
guipy/layouts/__init__.py
guipy/layouts/base.py
guipy/plugins/__init__.py
guipy/plugins/base.py
guipy/plugins/data_table/__init__.py
guipy/plugins/data_table/plugin.py
guipy/plugins/data_table/formatters/__init__.py
guipy/plugins/data_table/formatters/base.py
guipy/plugins/data_table/formatters/core.py
guipy/plugins/data_table/formatters/csv.py
guipy/plugins/data_table/formatters/npz.py
guipy/plugins/data_table/widgets/__init__.py
guipy/plugins/data_table/widgets/data_table.py
guipy/plugins/data_table/widgets/headers.py
guipy/plugins/data_table/widgets/model.py
guipy/plugins/data_table/widgets/selection_model.py
guipy/plugins/data_table/widgets/view.py
guipy/plugins/figure/__init__.py
guipy/plugins/figure/config.py
guipy/plugins/figure/plugin.py
guipy/plugins/figure/widgets/__init__.py
guipy/plugins/figure/widgets/canvas.py
guipy/plugins/figure/widgets/figure.py
guipy/plugins/figure/widgets/manager.py
guipy/plugins/figure/widgets/options.py
guipy/plugins/figure/widgets/plot_entry.py
guipy/plugins/figure/widgets/toolbar.py
guipy/plugins/figure/widgets/types/__init__.py
guipy/plugins/figure/widgets/types/base.py
guipy/plugins/figure/widgets/types/core.py
guipy/plugins/figure/widgets/types/histogram.py
guipy/plugins/figure/widgets/types/line.py
guipy/plugins/figure/widgets/types/scatter.py
guipy/plugins/figure/widgets/types/props/__init__.py
guipy/plugins/figure/widgets/types/props/base.py
guipy/plugins/figure/widgets/types/props/core.py
guipy/plugins/figure/widgets/types/props/data.py
guipy/plugins/figure/widgets/types/props/histogram.py
guipy/plugins/figure/widgets/types/props/line.py
guipy/plugins/figure/widgets/types/props/marker.py
guipy/utils/__init__.py
guipy/widgets/__init__.py
guipy/widgets/base.py
guipy-0.0.2.dist-info/LICENSE
guipy-0.0.2.dist-info/METADATA
guipy-0.0.2.dist-info/WHEEL
guipy-0.0.2.dist-info/entry_points.txt
guipy-0.0.2.dist-info/top_level.txt
guipy-0.0.2.dist-info/RECORD
