Metadata-Version: 2.1
Name: guipy
Version: 0.0.2
Summary: An easy plotting GUI for Python
Home-page: https://www.github.com/1313e/GuiPy
Author: Ellert van der Velden
Author-email: ellert_vandervelden@outlook.com
License: BSD-3
Keywords: gui plotting python
Platform: Windows
Platform: Mac OS-X
Platform: Linux
Platform: Unix
Classifier: Development Status :: 3 - Alpha
Classifier: Intended Audience :: Developers
Classifier: License :: OSI Approved :: BSD License
Classifier: Natural Language :: English
Classifier: Operating System :: MacOS
Classifier: Operating System :: Microsoft :: Windows
Classifier: Operating System :: Unix
Classifier: Programming Language :: Python
Classifier: Programming Language :: Python :: 3
Classifier: Programming Language :: Python :: 3.6
Classifier: Programming Language :: Python :: 3.7
Classifier: Programming Language :: Python :: 3.8
Classifier: Topic :: Scientific/Engineering :: Visualization
Classifier: Topic :: Software Development :: Libraries :: Python Modules
Classifier: Topic :: Utilities
Requires-Python: >=3.6, <4
Requires-Dist: cmasher (>=1.3.3)
Requires-Dist: e13tools (>=0.6.16)
Requires-Dist: matplotlib (>=2.2.4)
Requires-Dist: numpy (>=1.16.0)
Requires-Dist: pandas (>=0.24.0)
Requires-Dist: pyqt5 (==5.12.*)
Requires-Dist: qtpy (>=1.9.0)
Requires-Dist: sortedcontainers (>=1.5.9)
